<?xml version="1.0" encoding="utf-8"?>
<!DOCTYPE hibernate-mapping PUBLIC "-//Hibernate/Hibernate Mapping DTD 3.0//EN"
"http://hibernate.sourceforge.net/hibernate-mapping-3.0.dtd">
<!-- 
    Mapping file autogenerated by MyEclipse Persistence Tools
-->
<hibernate-mapping>
    <class name="com.sys.pm.po.PmWkyNetaccount" table="PM_WKY_NETACCOUNT" schema="SIFD">
        <id name="accountId" type="java.lang.String">
            <column name="ACCOUNT_ID" length="25" />
            <generator class="assigned" />
        </id>
        <property name="accountName" type="java.lang.String">
            <column name="ACCOUNT_NAME" length="64" not-null="true" />
        </property>
        <property name="accountPassword" type="java.lang.String">
            <column name="ACCOUNT_PASSWORD" length="64" not-null="true" />
        </property>
        <property name="accountSecpassword" type="java.lang.String">
            <column name="ACCOUNT_SECPASSWORD" length="64" />
        </property>
        <property name="accountLrsj" type="java.lang.String">
            <column name="ACCOUNT_LRSJ" length="14" not-null="true" />
        </property>
        <property name="accountLrr" type="java.lang.String">
            <column name="ACCOUNT_LRR" length="25" not-null="true" />
        </property>
        <property name="accountLrrxm" type="java.lang.String">
            <column name="ACCOUNT_LRRXM" length="16" />
        </property>
        <property name="accountSfky" type="java.lang.String">
            <column name="ACCOUNT_SFKY" length="1" not-null="true" />
        </property>
        <property name="accountNetkeywords" type="java.lang.String">
            <column name="ACCOUNT_NETKEYWORDS" length="256" />
        </property>
        <property name="accountNeturl" type="java.lang.String">
            <column name="ACCOUNT_NETURL" length="2000" />
        </property>
        <property name="accountBz" type="java.lang.String">
            <column name="ACCOUNT_BZ" length="2500" />
        </property>
    </class>
</hibernate-mapping>
